trame/modules/dataclass.py
trame/widgets/dataclass.py
trame_dataclass/__init__.py
trame_dataclass/core.py
trame_dataclass/module/__init__.py
trame_dataclass/module/protocol.py
trame_dataclass/module/serve/trame_dataclass.umd.js
trame_dataclass/widgets/__init__.py
trame_dataclass/widgets/dataclass.py
trame_dataclass-1.3.1.dist-info/METADATA
trame_dataclass-1.3.1.dist-info/WHEEL
trame_dataclass-1.3.1.dist-info/licenses/LICENSE
trame_dataclass-1.3.1.dist-info/RECORD
