Metadata-Version: 2.4
Name: trame-dataclass
Version: 1.3.1
Summary: Dataclass for trame UI binding
Author: Kitware Inc.
License: Apache Software License
License-File: LICENSE
Keywords: Application,Framework,Interactive,Python,Web
Classifier: Development Status :: 4 - Beta
Classifier: Environment :: Web Environment
Classifier: License :: OSI Approved :: Apache Software License
Classifier: Natural Language :: English
Classifier: Operating System :: OS Independent
Classifier: Programming Language :: Python :: 3 :: Only
Classifier: Topic :: Software Development :: Libraries :: Application Frameworks
Classifier: Topic :: Software Development :: Libraries :: Python Modules
Requires-Python: >=3.9
Requires-Dist: loguru
Requires-Dist: trame-client>=3.10
Provides-Extra: app
Requires-Dist: pywebview; extra == 'app'
Provides-Extra: dev
Requires-Dist: nox; extra == 'dev'
Requires-Dist: pre-commit; extra == 'dev'
Requires-Dist: pytest-asyncio; extra == 'dev'
Requires-Dist: pytest-cov>=3; extra == 'dev'
Requires-Dist: pytest>=6; extra == 'dev'
Requires-Dist: ruff; extra == 'dev'
Requires-Dist: trame; extra == 'dev'
Provides-Extra: jupyter
Requires-Dist: jupyterlab; extra == 'jupyter'
